{
  "namespace": "Project.Blueprint",
  "items": {
    "includes": [
	   {
        "name": "layouts",
        "path": "/sitecore/layout/Layouts/Project/Blueprint"
      },
      {
        "name": "forms",
        "path": "/sitecore/Forms/Blueprint"
      },
      {
        "name": "dictionary",
        "path": "/sitecore/system/Dictionary/Blueprint"
      },
      {
        "name": "templates",
        "path": "/sitecore/templates/Project/Blueprint"
      },
      {
        "name": "content",
        "path": "/sitecore/content/Blueprint"
      }
    ]
  }
}

